Workbook

Sheet 00 Start here
A1: Playwright Gym — 300 VS Code practice questions
A2: One spec file per row. No Page Object classes on Gym. Fixtures + JSON / CSV / Excel readers ARE in scope. Target: Playwright Gym v2 at http://localhost:4173 (widget origin http://127.0.0.1:4174)
A4: How you work | B4: For each row create tests/gym/{easy|medium|tough}/{Spec file} with a single test() (or a small generated pack from a data file when the task says so). Use fixtures/gym.js instead of repeating goto. Do not modify the gym app — treat it as a black box.
A5: Gym facts | B5: App http://localhost:4173. Payment widget origin http://127.0.0.1:4174 (room 14). Calendar today pinned to 2026-08-03. server.js serves /api/* and the second port — python http.server is not enough. X-ray test IDs and Hide test IDs live in the sidebar. Activity log records clicks, consent, login, popups, routes. tour.spec.js now includes rooms 09–14. Read it, then write YOUR files.
A6: Locator default (interview order) | B6: getByRole → getByLabel → getByPlaceholder → getByText → getByTestId → css/xpath last. Gym gives data-testid so you can learn; many medium/tough rows ban a particular hook on purpose.
A7: Pass bar | B7: A row is Done only when npx playwright test <that spec> is green without waitForTimeout / page.waitForTimeout / hard sleep. Traces stay on-failure.
A8: Suggested order | B8: E-001…E-006 repo + fixtures. Home (Fifteen rooms, two Saves, hide-testid) then Controls/Files. Rooms 09–14 start in Easy so you touch overlays/lists/network/session/widgets/origins before Medium. Medium = route.fulfill before goto, storageState, clock, virtual scroll, portal combobox. Tough = strict Save collisions, windowed lists, clock bounds, cross-origin token + journeys.
A9: Commands | B9: cd playwright-gym && node server.js 4173 (or let webServer start it) npx playwright test tests/gym/easy/E-019.spec.js --headed npx playwright test tests/gym/easy --project=chromium npx playwright test tests/gym/tough/T-001.spec.js --trace on npx playwright show-report npx playwright show-trace test-results/.../trace.zip
A10: Repo layout to create | B10: gym-practice/ playwright.config.js fixtures/gym.js, shots.js, downloads.js, testdata.js helpers/readJson.js, readCsv.js, readXlsx.js, constants.js, frames.js, shadow.js, cal.js, acc.js data/*.json, *.csv, *.xlsx (you author these) tests/gym/easy/E-001.spec.js … E-100.spec.js tests/gym/medium/M-001.spec.js … tests/gym/tough/T-001.spec.js …
A11: Fixture / data column | B11: Build that helper or file if it does not exist yet, then use it in the spec. Reuse — do not copy-paste fs.readFile into every test. File-driven UI tests show up in both India and Germany SDET interviews.
A12: Status column | B12: Not started → In progress → Done / Stuck. Progress sheet formulas read column L. Green Done, amber In progress, red Stuck.
A13: Interview mapping | B13: Easy = drive v2 Gym including new rooms. Medium = production APIs (route, storageState, clock, portals). Tough = strict-mode name collisions, virtualisation, too-late routes, clock bounds, cross-origin. Business keys still win: SHP-4103, SHP-9800, INV-2201 — never nth.
A14: Do not | B14: Do not build a POM layer for Gym. Do not call the gym’s own tests from your suite. Do not scrape tour.spec.js into your files — rewrite. Do not use XPath unless a row asks you to compare it with getByRole.
A15: After Gym | B15: Kestrel-Bank (4001) and Heron-Health (4002) are next — those WILL use POM + storageState + API fixture. Hearthline is the lab course of traps. Finish at least 80 easy + 50 medium + 25 tough here before switching sites.
A17: Counts | B17: 100 Easy + 100 Medium + 100 Tough = 300 specs. Progress sheet tracks Done % per level and per module.
A19: Colour legend
A20: Easy tab
A21: Medium tab
A22: Tough tab
A23: Done
A24: In progress
A25: Stuck

Sheet 01 Easy
A1: ID | B1: Level | C1: Module | D1: Page | E1: Spec file | F1: Task — write this as one spec in VS Code | G1: Start from / hooks | H1: Hint (API, not a full solution) | I1: Pass when | J1: Skills | K1: Fixture / data | L1: Status | M1: My notes
A2: E-001 | B2: Easy | C2: Setup | D2: repo root | E2: E-001.spec.js | F2: Create sibling gym-practice. Install @playwright/test. Config baseURL http://localhost:4173 and webServer `node ../playwright-gym/server.js 4173` (v2 also binds 4174). | G2: Do not edit gym | H2: defineConfig + webServer | I2: --list works | J2: config | K2: playwright.config.js | L2: Not started
A3: E-002 | B3: Easy | C3: Setup | D3: repo root | E3: E-002.spec.js | F3: Add fixtures/gym.js test.extend({ openGym }) that goto+returns page. | G3: reuse in later specs | H3: test.extend | I3: openGym('/pages/controls.html') works | J3: fixtures | K3: fixtures/gym.js | L3: Not started
A4: E-003 | B4: Easy | C4: Setup | D4: repo root | E4: E-003.spec.js | F4: Add fixtures/shots.js: on failure write fullPage PNG via testInfo. | G4: practice attach | H4: testInfo.attach | I4: failed spec produces PNG | J4: screenshot fixture | K4: fixtures/shots.js | L4: Not started
A5: E-004 | B5: Easy | C5: Setup | D5: repo root | E5: E-004.spec.js | F5: Implement readJson, readCsv, readXlsx helpers and prove each on a tiny data/ file. | G5: you author data/ | H5: fs + exceljs | I5: three reads succeed | J5: file readers | K5: helpers/* | L5: Not started
A6: E-005 | B6: Easy | C6: Setup | D6: repo root | E6: E-005.spec.js | F6: constants.js exports BASE, GYM_TODAY=2026-08-03, ORIGIN_WIDGET=http://127.0.0.1:4174, MODULES with all 15 page paths. | G6: v2 has 15 rooms | H6: named exports | I6: MODULES.length === 15 | J6: constants | K6: helpers/constants.js | L6: Not started
A7: E-006 | B7: Easy | C7: Setup | D7: repo root | E7: E-006.spec.js | F7: Add npm scripts test:easy test:medium test:tough. | G7: daily driver | H7: package.json | I7: test:easy --list shows E- files | J7: scripts | K7: package.json | L7: Not started
A8: E-007 | B8: Easy | C8: Home | D8: /index.html | E8: E-007.spec.js | F8: Assert h1 contains Fifteen rooms (v2 copy, not Nine). | G8: home | H8: getByRole heading level 1 | I8: phrase present | J8: goto | K8: - | L8: Not started
A9: E-008 | B9: Easy | C9: Home | D9: /index.html | E9: E-008.spec.js | F9: Assert 14 bench cards bench-controls through bench-origins. | G9: testid prefix bench- | H9: toHaveCount(14) | I9: 14 cards | J9: count | K9: - | L9: Not started
A10: E-009 | B10: Easy | C10: Home | D10: /index.html | E10: E-009.spec.js | F10: Click bench-overlays, land on overlays.html, nav-00 back home. | G10: new room | H10: getByTestId | I10: round trip | J10: nav | K10: - | L10: Not started
A11: E-010 | B11: Easy | C11: Home | D11: /index.html | E11: E-010.spec.js | F11: Click #warmup Ready buttons 3 then 1 then 2. Assert #warm-out contains correct. | G11: no testids | H11: nth() | I11: sequence correct | J11: nth | K11: - | L11: Not started
A12: E-011 | B12: Easy | C12: Home | D12: /index.html | E12: E-011.spec.js | F12: Click Save inside #warmup-header not #warmup-lane. Assert #warm-save-out is header save. | G12: v2 two Saves | H12: region.getByRole | I12: header save | J12: scope | K12: - | L12: Not started
A13: E-012 | B13: Easy | C13: Home | D13: /index.html | E13: E-012.spec.js | F13: Toggle X-ray on then off via xray-toggle. | G13: sidebar | H13: getByTestId('xray-toggle') | I13: class/log flips | J13: toggle | K13: - | L13: Not started
... A101: E-100 | B101: Easy | C101: Origins | D101: /pages/origins.html | E101: E-100.spec.js | F101: Grant clipboard, clip-write then clip-read. clip-input non-empty. | G101: clipboard-read/write | H101: grantPermissions | I101: round trip | J101: clipboard | K101: - | L101: Not started

Sheet 02 Medium
A1: ID | B1: Level | C1: Module | D1: Page | E1: Spec file | F1: Task — write this as one spec in VS Code | G1: Start from / hooks | H1: Hint (API, not a full solution) | I1: Pass when | J1: Skills | K1: Fixture / data | L1: Status | M1: My notes
A2: M-001 | B2: Medium | C2: Controls | D2: /pages/controls.html | E2: M-001.spec.js | F2: Prove input-keystroke rejects fill('pasted') and accepts pressSequentially('typed'). | G2: trap | H2: fill vs pressSequentially | I2: both asserts | J2: pressSequentially | K2: - | L2: Not started
A3: M-002 | B3: Medium | C3: Controls | D3: /pages/controls.html | E3: M-002.spec.js | F3: Type 4242424242424242 into input-masked. Assert formatted spaces, not raw 16 digits. | G3: mask | H3: toHaveValue | I3: spaces present | J3: mask | K3: - | L3: Not started
A4: M-003 | B4: Medium | C4: Controls | D4: /pages/controls.html | E4: M-003.spec.js | F4: Type ' padded ' into input-trim, blur, value is trimmed. | G4: blur | H4: press Tab | I4: trimmed | J4: trim | K4: - | L4: Not started
A5: M-004 | B5: Medium | C5: Controls | D5: /pages/controls.html | E5: M-004.spec.js | F5: Turn switch-input on via label click OR check({force:true}). Assert checked. | G5: 1x1 input | H5: force or label | I5: checked | J5: force | K5: - | L5: Not started
A6: M-005 | B6: Medium | C6: Controls | D6: /pages/controls.html | E6: M-005.spec.js | F6: Type val into typeahead. Wait typeahead-status count. Exactly 2 options. | G6: 450ms debounce | H6: no sleep | I6: 2 options | J6: debounce | K6: - | L6: Not started
A7: M-006 | B7: Medium | C7: Controls | D7: /pages/controls.html | E7: M-006.spec.js | F7: Parent checkbox: tick EMEA+APAC+AMER then untick AMER. Assert indeterminate again. | G7: tri-state | H7: evaluate | I7: indeterminate | J7: checkbox tree | K7: - | L7: Not started
A8: M-007 | B8: Medium | C8: Controls | D8: /pages/controls.html | E8: M-007.spec.js | F8: Click aria-disabled-btn with {force:true}. Decide and assert whether out stays blocked (page still guards) or published. | G8: v2 | H8: force vs guard | I8: documented assert | J8: aria-disabled force | K8: - | L8: Not started
A9: M-008 | B9: Medium | C9: Tables | D9: /pages/tables.html | E9: M-008.spec.js | F9: Read 3rd row ref at page size 10, switch to 5, show nth(2) identity change after sort. | G9: pager+sort | H9: nth vs key | I9: assertion proves it | J9: nth trap | K9: - | L9: Not started
A10: M-009 | B10: Medium | C10: Tables | D10: /pages/tables.html | E10: M-009.spec.js | F10: Delete SHP-4102. Its locator count becomes 0. | G10: data-ship | H10: toHaveCount(0) | I10: gone | J10: delete | K10: - | L10: Not started
A11: M-010 | B11: Medium | C11: Tables | D11: /pages/tables.html | E11: M-010.spec.js | F11: Sum visible weight cells and compare to foot-weight. | G11: footer | H11: evaluate numbers | I11: match | J11: footer | K11: - | L11: Not started
A12: M-011 | B12: Medium | C12: Tables | D12: /pages/tables.html | E12: M-011.spec.js | F12: Edit a quota cell, commit Enter, assert new text. | G12: cell-editor | H12: press Enter | I12: text | J12: inline edit | K12: - | L12: Not started
A13: M-012 | B13: Medium | C13: Tables | D13: /pages/tables.html | E13: M-012.spec.js | F13: Count inner-table rows without counting merged-table outer rows. | G13: nested table | H13: locator scoped | I13: inner only | J13: scope | K13: - | L13: Not started
... A101: M-100 | B101: Medium | C101: Fixtures | D101: repo root | E101: M-100.spec.js | F101: downloads.js unique dir per test; use it when saving invoice-less blob downloads from files.html. | G101: isolation | H101: testInfo | I101: no collide | J101: download fixture | K101: fixtures/downloads.js | L101: Not started

Sheet 03 Tough
A1: ID | B1: Level | C1: Module | D1: Page | E1: Spec file | F1: Task — write this as one spec in VS Code | G1: Start from / hooks | H1: Hint (API, not a full solution) | I1: Pass when | J1: Skills | K1: Fixture / data | L1: Status | M1: My notes
A2: T-001 | B2: Tough | C2: Frames | D2: /pages/frames.html | E2: T-001.spec.js | F2: Fill real depth-4 deep-input without selector strings containing depth-2 or depth-4. Click deep-confirm. Relay set. | G2: titles/nth/src | H2: frameLocator iframe nth | I2: relay | J2: ambiguous frames | K2: - | L2: Not started
A3: T-002 | B3: Tough | C3: Frames | D3: /pages/frames.html | E3: T-002.spec.js | F3: Innermost deep-confirm is inside shadow in frame 4. Click it after fill using role or host, not a guessed css piercing. | G3: level-4 shadow | H3: frame chain then getByRole | I3: relay | J3: frame+shadow | K3: - | L3: Not started
A4: T-003 | B4: Tough | C4: Frames | D4: /pages/frames.html | E4: T-003.spec.js | F4: All sibling panel-tag values unique including injected and shadow-hosted. | G4: five panels | H4: frameLocator each | I4: unique set | J4: siblings | K4: - | L4: Not started
A5: T-004 | B5: Tough | C5: Frames | D5: /pages/frames.html | E5: T-004.spec.js | F5: Fill depth 4 using ONLY positional frameLocator('iframe').nth chain. | G5: no ids | H5: nth | I5: relay | J5: nth frames | K5: - | L5: Not started
A6: T-005 | B6: Tough | C6: Frames | D6: /pages/frames.html | E6: T-005.spec.js | F6: Prove a locator that stops at depth 1 passes fill but relay empty — attach screenshot of both locators highlighted if possible. | G6: decoy | H6: highlight optional | I6: relay empty vs filled | J6: evidence | K6: fixtures/shots.js | L6: Not started
A7: T-006 | B7: Tough | C7: Frames | D7: /pages/frames.html | E7: T-006.spec.js | F7: srcdoc click twice and late-frame fill in ONE spec with test.step. | G7: two frame types | H7: test.step | I7: both pass | J7: steps | K7: - | L7: Not started
A8: T-007 | B8: Tough | C8: Frames | D8: /pages/frames.html | E8: T-007.spec.js | F8: Helper helpers/frames.js depth4(page). Use it here and in one other spec (comment the reuse). | G8: DRY | H8: helper | I8: relay | J8: helper | K8: helpers/frames.js | L8: Not started
A9: T-008 | B9: Tough | C9: Frames | D9: /pages/frames.html | E9: T-008.spec.js | F9: Table-cell frames: read all three site tags JP/EU/US if present; at least osaka JP-W2. | G9: data-site | H9: row.frameLocator | I9: JP-W2 | J9: table frames | K9: - | L9: Not started
A10: T-009 | B10: Tough | C10: DOM | D10: /pages/dom.html | E10: T-009.spec.js | F10: Locator vs ElementHandle: click detach-go. locator text Replacement; handle isConnected false. | G10: stale handle | H10: elementHandle | I10: contrast | J10: stale | K10: - | L10: Not started
A11: T-010 | B11: Tough | C11: DOM | D11: /pages/dom.html | E11: T-010.spec.js | F11: Click canvas at offset {x:70,y:45}. canvas-out Accept. | G11: painted target | H11: click position | I11: Accept | J11: canvas | K11: - | L11: Not started
A12: T-011 | B12: Tough | C12: DOM | D12: /pages/dom.html | E12: T-011.spec.js | F12: SVG APAC click. svg-out typeof className = object. | G12: className not string | H12: data-region | I12: object | J12: SVG | K12: - | L12: Not started
A13: T-012 | B13: Tough | C13: DOM | D13: /pages/dom.html | E13: T-012.spec.js | F13: prop-input fill changed. getAttribute value still initial; toHaveValue changed. | G13: attr vs prop | H13: getAttribute vs toHaveValue | I13: both | J13: property | K13: - | L13: Not started
... A101: T-100 | B101: Tough | C101: Config | D101: repo root | E101: T-100.spec.js | F101: Add a chromium-only project gym-v2 with permissions clipboard and geolocation so origins specs do not repeat grantPermissions. Prove one origins spec uses it. | G101: projects | H101: test.use / project use | I101: geo spec green | J101: project perms | K101: playwright.config.js | L101: Not started

Sheet 04 Fixtures & data
A1: Kind | B1: Path | C1: What to implement | D1: Used by (examples)
A2: Fixture | B2: fixtures/gym.js | C2: test.extend({ openGym }). openGym(path, opts?) → page after goto. Optional opts.xray toggles sidebar X-ray. Not a class. | D2: Almost every spec
A3: Fixture | B3: fixtures/shots.js | C3: On failure: fullPage screenshot under test-results/screenshots/{titlePath}.png using testInfo. | D3: E-007, T-010, journeys
A4: Fixture | B4: fixtures/downloads.js | C4: Unique directory per test (workerIndex + sanitized title). acceptDownloads already true in config. Teardown fs.rmSync recursive. | D4: E-083+, M-052+, T-073+
A5: Fixture | B5: fixtures/testdata.js | C5: Worker-scoped. Preload users.json, shipments.csv, any xlsx. Expose { users, shipments, sheets }. | D5: M-091, T-057, T-094
A6: Fixture | B6: fixtures/timing.js | C6: Auto fixture appending start/end ISO timestamps to test-results/timing.csv. | D6: T-099
A7: Helper | B7: helpers/readJson.js | C7: readJson(relPath) → object. Throw with the path if missing / invalid JSON. | D7: E-004, E-041, T-085
A8: Helper | B8: helpers/readCsv.js | C8: Header row → array of objects. Trim cells. Handle CRLF. Used on gym assets/downloads/shipments.csv and on saveAs copies. | D8: E-005, E-048, T-075
A9: Helper | B9: helpers/readXlsx.js | C9: exceljs preferred. First sheet to objects. Keep raw values (no date-serial surprise). | D9: E-006, M-048, T-094
A10: Helper | B10: helpers/constants.js | C10: GYM_TODAY='2026-08-03'; BASE='http://localhost:4173'; ORIGIN_WIDGET='http://127.0.0.1:4174'; MODULES = 15 page paths. | D10: Setup, calendars, origins
A11: Helper | B11: helpers/abs.js | C11: Resolve a path from repo root. Throw if missing. | D11: M-098
A12: Helper | B12: helpers/frames.js | C12: depth4(page) frameLocator chain. lateFrame(page), sibling(page, side). | D12: T-005+
... A47: Note | B47: Do not edit gym | C47: Practice repo is a sibling of playwright-gym. webServer.command can be `node ../playwright-gym/server.js 4173`. Leave tour.spec.js alone. | D47: All

Sheet 05 Progress
A1: Progress — change Status on the question sheets; these formulas update
A3: Level | B3: Total | C3: Done | D3: In progress | E3: Stuck | F3: Not started | G3: Done %
A4: Easy | B4: 100 | C4: =COUNTIF('01 Easy'!L:L,"Done") -> 0 | D4: =COUNTIF('01 Easy'!L:L,"In progress") -> 0 | E4: =COUNTIF('01 Easy'!L:L,"Stuck") -> 0 | F4: =COUNTIF('01 Easy'!L:L,"Not started") -> 100 | G4: =IF(B4=0,0,C4/B4) -> 0
A5: Medium | B5: 100 | C5: =COUNTIF('02 Medium'!L:L,"Done") -> 0 | D5: =COUNTIF('02 Medium'!L:L,"In progress") -> 0 | E5: =COUNTIF('02 Medium'!L:L,"Stuck") -> 0 | F5: =COUNTIF('02 Medium'!L:L,"Not started") -> 100 | G5: =IF(B5=0,0,C5/B5) -> 0
A6: Tough | B6: 100 | C6: =COUNTIF('03 Tough'!L:L,"Done") -> 0 | D6: =COUNTIF('03 Tough'!L:L,"In progress") -> 0 | E6: =COUNTIF('03 Tough'!L:L,"Stuck") -> 0 | F6: =COUNTIF('03 Tough'!L:L,"Not started") -> 100 | G6: =IF(B6=0,0,C6/B6) -> 0
A7: ALL | B7: =SUM(B4:B6) -> 300 | C7: =SUM(C4:C6) -> 0 | D7: =SUM(D4:D6) -> 0 | E7: =SUM(E4:E6) -> 0 | F7: =SUM(F4:F6) -> 300 | G7: =IF(B7=0,0,C7/B7) -> 0
A9: Module coverage (question counts, not completion)
A11: Module | B11: Easy | C11: Medium | D11: Tough | E11: Total
A12: Setup | B12: =COUNTIF('01 Easy'!C:C,A12) -> 6 | C12: =COUNTIF('02 Medium'!C:C,A12) -> 0 | D12: =COUNTIF('03 Tough'!C:C,A12) -> 0 | E12: =SUM(B12:D12) -> 6
A13: Home | B13: =COUNTIF('01 Easy'!C:C,A13) -> 8 | C13: =COUNTIF('02 Medium'!C:C,A13) -> 0 | D13: =COUNTIF('03 Tough'!C:C,A13) -> 1 | E13: =SUM(B13:D13) -> 9
A14: Controls | B14: =COUNTIF('01 Easy'!C:C,A14) -> 11 | C14: =COUNTIF('02 Medium'!C:C,A14) -> 7 | D14: =COUNTIF('03 Tough'!C:C,A14) -> 4 | E14: =SUM(B14:D14) -> 22
A15: Tables | B15: =COUNTIF('01 Easy'!C:C,A15) -> 7 | C15: =COUNTIF('02 Medium'!C:C,A15) -> 8 | D15: =COUNTIF('03 Tough'!C:C,A15) -> 6 | E15: =SUM(B15:D15) -> 21
A16: Accordions | B16: =COUNTIF('01 Easy'!C:C,A16) -> 5 | C16: =COUNTIF('02 Medium'!C:C,A16) -> 5 | D16: =COUNTIF('03 Tough'!C:C,A16) -> 4 | E16: =SUM(B16:D16) -> 14
A17: Calendars | B17: =COUNTIF('01 Easy'!C:C,A17) -> 5 | C17: =COUNTIF('02 Medium'!C:C,A17) -> 5 | D17: =COUNTIF('03 Tough'!C:C,A17) -> 4 | E17: =SUM(B17:D17) -> 14
A18: Files | B18: =COUNTIF('01 Easy'!C:C,A18) -> 7 | C18: =COUNTIF('02 Medium'!C:C,A18) -> 6 | D18: =COUNTIF('03 Tough'!C:C,A18) -> 5 | E18: =SUM(B18:D18) -> 18
A19: Frames | B19: =COUNTIF('01 Easy'!C:C,A19) -> 3 | C19: =COUNTIF('02 Medium'!C:C,A19) -> 5 | D19: =COUNTIF('03 Tough'!C:C,A19) -> 8 | E19: =SUM(B19:D19) -> 16
A20: DOM | B20: =COUNTIF('01 Easy'!C:C,A20) -> 4 | C20: =COUNTIF('02 Medium'!C:C,A20) -> 5 | D20: =COUNTIF('03 Tough'!C:C,A20) -> 8 | E20: =SUM(B20:D20) -> 17
A21: Shadow | B21: =COUNTIF('01 Easy'!C:C,A21) -> 3 | C21: =COUNTIF('02 Medium'!C:C,A21) -> 4 | D21: =COUNTIF('03 Tough'!C:C,A21) -> 6 | E21: =SUM(B21:D21) -> 13
A22: Overlays | B22: =COUNTIF('01 Easy'!C:C,A22) -> 8 | C22: =COUNTIF('02 Medium'!C:C,A22) -> 9 | D22: =COUNTIF('03 Tough'!C:C,A22) -> 8 | E22: =SUM(B22:D22) -> 25
A23: Lists | B23: =COUNTIF('01 Easy'!C:C,A23) -> 7 | C23: =COUNTIF('02 Medium'!C:C,A23) -> 9 | D23: =COUNTIF('03 Tough'!C:C,A23) -> 8 | E23: =SUM(B23:D23) -> 24
... A31: Cross | B31: =COUNTIF('01 Easy'!C:C,A31) -> 0 | C31: =COUNTIF('02 Medium'!C:C,A31) -> 0 | D31: =COUNTIF('03 Tough'!C:C,A31) -> 3 | E31: =SUM(B31:D31) -> 3
A34: How to use
A35: 1. Filter Status = Not started on 01 Easy and work top to bottom. 2. Mark In progress when the spec file exists. Mark Done only on a green run. 3. Stuck = you needed tour.spec.js to cheat — go back and rewrite without copying.

Sheet 06 Skills map
A1: Skill cluster | B1: Learn it on | C1: Then prove it on
A2: goto / title / heading | B2: E-009 Home | C2: E-018 loop all modules
A3: getByTestId / getByRole | B3: E-010 bench cards | C3: M-008 custom listbox
A4: fill / check / selectOption | B4: E-019…E-027 Controls | C4: T-086 dependent select
A5: pressSequentially / mask / trim | B5: M-001…M-003 | C5: T-085 awkward pack
A6: dialogs + popup + toast | B6: E-034…E-038 | C6: T-093 dialog pack
A7: web-first waits / no sleep | B7: E-032 delayed button | C7: M-022 live poll, T-049 live flake
A8: screenshots + report attach | B8: E-014, E-015, E-056 | C8: T-010 decoy vs real, T-101 attach
A9: fixtures test.extend | B9: E-003, E-007 | C9: T-098 options, T-099 auto
A10: JSON reader | B10: E-004, E-041, E-076 | C10: T-067, T-085, T-095
A11: CSV reader | B11: E-005, E-048, E-085 | C11: T-075 generated report
A12: XLSX reader + matrix tests | B12: E-006, E-090 | C12: T-057, T-081, T-094
... A41: aria-disabled / late testid / exe drop | B41: Easy Controls/DOM/Files | C41: Medium force vs guard
